dendrodict/__init__.py
dendrodict-1.0.4.dist-info/LICENSE
dendrodict-1.0.4.dist-info/METADATA
dendrodict-1.0.4.dist-info/WHEEL
dendrodict-1.0.4.dist-info/top_level.txt
dendrodict-1.0.4.dist-info/RECORD
