Metadata-Version: 2.1
Name: dendrodict
Version: 1.0.4
Summary: Dict type that makes it easier to work with deeply nested dicts.
Home-page: http://bitbucket.org/sixty-north/dendrodict
Author: Sixty North AS
Author-email: rob@sixty-north.com
License: MIT
Platform: any
Classifier: Development Status :: 3 - Alpha
Classifier: Operating System :: OS Independent
Classifier: Programming Language :: Python
Classifier: Programming Language :: Python :: 3 :: Only
License-File: LICENSE
Provides-Extra: dev
Requires-Dist: black ; extra == 'dev'
Requires-Dist: bump2version ; extra == 'dev'
Requires-Dist: twine ; extra == 'dev'
Provides-Extra: test
Requires-Dist: hypothesis ; extra == 'test'
Requires-Dist: pytest ; extra == 'test'
